dj_sentry/__init__.py
dj_sentry/apps.py
dj_sentry-0.2.0.dist-info/LICENSE.md
dj_sentry-0.2.0.dist-info/WHEEL
dj_sentry-0.2.0.dist-info/METADATA
dj_sentry-0.2.0.dist-info/RECORD
