Metadata-Version: 2.1
Name: dj-sentry
Version: 0.2.0
Summary: A Django app to initialize Sentry client for your Django applications
Home-page: https://github.com/themimitoof/dj_sentry
License: BSD-3-Clause
Keywords: django,sentry
Author: Michael Vieira
Author-email: dev@mvieira.fr
Requires-Python: >=3.6.2,<4.0.0
Classifier: License :: OSI Approved :: BSD License
Classifier: Programming Language :: Python :: 3
Classifier: Programming Language :: Python :: 3.10
Classifier: Programming Language :: Python :: 3.7
Classifier: Programming Language :: Python :: 3.8
Classifier: Programming Language :: Python :: 3.9
Requires-Dist: django (>=3.0,<5.0)
Requires-Dist: sentry-sdk (>=1.5.0,<2.0.0)
Project-URL: Repository, https://github.com/themimitoof/dj_sentry
